custom_admin_views/__init__.py
custom_admin_views/admin.py
custom_admin_views/models.py
custom_admin_views/templatetags/__init__.py
custom_admin_views/templatetags/admin_extras.py
django_admin_custom_views-1.0.0.dist-info/LICENSE
django_admin_custom_views-1.0.0.dist-info/METADATA
django_admin_custom_views-1.0.0.dist-info/WHEEL
django_admin_custom_views-1.0.0.dist-info/top_level.txt
django_admin_custom_views-1.0.0.dist-info/RECORD
