Metadata-Version: 2.1
Name: django-admin-custom-views
Version: 1.0.0
Summary: Create custom view for Django admin.
Home-page: https://github.com/ludel/django-admin-views
Author: Ludovic Delsol
Author-email: ludel47@gmail.com
License: APL
Platform: UNKNOWN
Classifier: Programming Language :: Python :: 3
Classifier: Environment :: Web Environment
Classifier: Framework :: Django
Classifier: Intended Audience :: Developers
Classifier: License :: OSI Approved :: MIT License
Classifier: Operating System :: OS Independent
Classifier: Topic :: Utilities
License-File: LICENSE
Requires-Dist: django
